indy_hub/__init__.py
indy_hub/admin.py
indy_hub/apps.py
indy_hub/auth_hooks.py
indy_hub/decorators.py
indy_hub/esi_helpers.py
indy_hub/migration_utils.py
indy_hub/models.py
indy_hub/notifications.py
indy_hub/schedules.py
indy_hub/signals.py
indy_hub/tasks.py
indy_hub/urls.py
indy_hub/utils.py
indy_hub/views.py
indy_hub/management/__init__.py
indy_hub/management/commands/__init__.py
indy_hub/management/commands/cache_esi_data.py
indy_hub/management/commands/cleanup_permissions.py
indy_hub/management/commands/esi_status.py
indy_hub/management/commands/populate_location_names.py
indy_hub/migrations/0001_initial.py
indy_hub/migrations/0002_blueprint_character_name_industryjob_character_name.py
indy_hub/migrations/0003_characterupdatetracker_last_refresh_request.py
indy_hub/migrations/0004_alter_characterupdatetracker_options_and_more.py
indy_hub/migrations/0006_blueprint_copy_share_and_request.py
indy_hub/migrations/0007_alter_blueprintcopyrequest_id_and_more.py
indy_hub/migrations/0008_add_copies_requested.py
indy_hub/migrations/0009_blueprintcopyoffer.py
indy_hub/migrations/0010_add_delivered_to_copyrequest.py
indy_hub/migrations/0011_alter_blueprintcopyoffer_id.py
indy_hub/migrations/0012_industryjob_job_completed_notified.py
indy_hub/migrations/0013_characterupdatetracker_jobs_notify_completed.py
indy_hub/migrations/0014_alter_blueprint_options_and_more.py
indy_hub/migrations/0015_migrate_to_charactersettings.py
indy_hub/migrations/0016_productionconfig.py
indy_hub/migrations/0017_add_production_simulation.py
indy_hub/migrations/0018_enhanced_production_simulation_models.py
indy_hub/migrations/0019_charactersettings_constraints.py
indy_hub/migrations/0020_charactersettings_sharing_scope.py
indy_hub/migrations/0021_blueprint_table_and_bp_type.py
indy_hub/migrations/0022_alter_blueprint_bp_type.py
indy_hub/migrations/0023_add_location_names_drop_facility_fields.py
indy_hub/migrations/0024_repopulate_location_names.py
indy_hub-1.13.11.dist-info/licenses/LICENSE
indy_hub-1.13.11.dist-info/WHEEL
indy_hub-1.13.11.dist-info/METADATA
indy_hub-1.13.11.dist-info/RECORD
