Metadata-Version: 2.4
Name: indy-hub
Version: 1.13.11
Summary: Indy Hub - An industrial management application for Alliance Auth
Keywords: allianceauth,eveonline,hub,industry,indy
Author-email: erka Ekanon <erkaekanon@outlook.com>
Requires-Python: >=3.10
Classifier: Environment :: Web Environment
Classifier: Framework :: Celery
Classifier: Framework :: Django
Classifier: Framework :: Django :: 4.0
Classifier: Framework :: Django :: 4.2
Classifier: Intended Audience :: Developers
Classifier: License :: OSI Approved :: MIT License
Classifier: Operating System :: OS Independent
Classifier: Programming Language :: Python
Classifier: Programming Language :: Python :: 3 :: Only
Classifier: Programming Language :: Python :: 3.10
Classifier: Programming Language :: Python :: 3.11
Classifier: Programming Language :: Python :: 3.12
Classifier: Programming Language :: Python :: 3.13
Classifier: Programming Language :: Python :: Implementation :: CPython
Classifier: Topic :: Internet :: WWW/HTTP
Classifier: Topic :: Internet :: WWW/HTTP :: Dynamic Content
License-File: LICENSE
Requires-Dist: aa-discordnotify>=2
Requires-Dist: allianceauth>=4,<5
Requires-Dist: django-eveuniverse>=1.5.7
Project-URL: Homepage, https://github.com/Erkaek/aa-Indy_Hub
Project-URL: Source, https://github.com/Erkaek/aa-Indy_Hub
Project-URL: Tracker, https://github.com/Erkaek/aa-Indy_Hub/issues
